linkvertise_bypasser/__init__.py
linkvertise_bypasser/linkvertise.py
linkvertise_bypasser/templates/__init__.py
linkvertise_bypasser/templates/cdpc_query.graphql
linkvertise_bypasser/templates/cdpc_query_min.graphql
linkvertise_bypasser/templates/gdpc_query.graphql
linkvertise_bypasser/templates/gdpc_query_min.graphql
linkvertise_bypasser/templates/gdpt_query.graphql
linkvertise_bypasser/templates/gdpt_query_min.graphql
linkvertise_bypasser-0.1.0.dist-info/LICENSE
linkvertise_bypasser-0.1.0.dist-info/METADATA
linkvertise_bypasser-0.1.0.dist-info/WHEEL
linkvertise_bypasser-0.1.0.dist-info/RECORD
