Metadata-Version: 2.1
Name: linkvertise-bypasser
Version: 0.1.0
Summary: Bypass linkvertise links using the internal API
License: MIT
Author: MRtecno98
Author-email: mr.tecno98@gmail.com
Requires-Python: >=3.10,<4.0
Classifier: License :: OSI Approved :: MIT License
Classifier: Programming Language :: Python :: 3
Classifier: Programming Language :: Python :: 3.10
Classifier: Programming Language :: Python :: 3.11
Classifier: Programming Language :: Python :: 3.12
Requires-Dist: requests (>=2.32.3,<3.0.0)
